MANIFEST.in
README.md
setup.py
word_tokenizer/__init__.py
word_tokenizer.egg-info/PKG-INFO
word_tokenizer.egg-info/SOURCES.txt
word_tokenizer.egg-info/dependency_links.txt
word_tokenizer.egg-info/top_level.txt